Metadata-Version: 2.1
Name: pipUpdateAll
Version: 1.0.0
Summary: Paquete para actualizar todos los paquetes instalados con 'pip'
Home-page: https://github.com/SurivZ/pip-update-all
Author: SurivZ
Author-email: franklinserrano23@email.com
Classifier: Development Status :: 5 - Production/Stable
Classifier: Intended Audience :: Developers
Classifier: License :: OSI Approved :: MIT License
Classifier: Operating System :: OS Independent
Classifier: Programming Language :: Python :: 3
Classifier: Programming Language :: Python :: 3.7
Classifier: Programming Language :: Python :: 3.8
Classifier: Programming Language :: Python :: 3.9
Classifier: Programming Language :: Python :: 3.10
Classifier: Topic :: Software Development :: Libraries :: Python Modules
Requires-Python: >=3
